odoo9_addon_web_translate_dialog-9.0.1.0.0-py2.7-nspkg.pth
odoo_addons/web_translate_dialog/__openerp__.py
odoo_addons/web_translate_dialog/__init__.py
odoo_addons/web_translate_dialog/README.rst
odoo_addons/web_translate_dialog/view/web_translate.xml
odoo_addons/web_translate_dialog/i18n/it.po
odoo_addons/web_translate_dialog/i18n/es.po
odoo_addons/web_translate_dialog/i18n/ar.po
odoo_addons/web_translate_dialog/i18n/tr.po
odoo_addons/web_translate_dialog/i18n/hr.po
odoo_addons/web_translate_dialog/i18n/sl.po
odoo_addons/web_translate_dialog/i18n/nl.po
odoo_addons/web_translate_dialog/i18n/de.po
odoo_addons/web_translate_dialog/i18n/fr.po
odoo_addons/web_translate_dialog/i18n/pt_BR.po
odoo_addons/web_translate_dialog/i18n/fi.po
odoo_addons/web_translate_dialog/i18n/web_translate_dialog.pot
odoo_addons/web_translate_dialog/static/description/icon.png
odoo_addons/web_translate_dialog/static/src/js/web_translate_dialog.js
odoo_addons/web_translate_dialog/static/src/css/base.css
odoo_addons/web_translate_dialog/static/src/xml/base.xml
odoo9_addon_web_translate_dialog-9.0.1.0.0.dist-info/top_level.txt
odoo9_addon_web_translate_dialog-9.0.1.0.0.dist-info/WHEEL
odoo9_addon_web_translate_dialog-9.0.1.0.0.dist-info/RECORD
odoo9_addon_web_translate_dialog-9.0.1.0.0.dist-info/metadata.json
odoo9_addon_web_translate_dialog-9.0.1.0.0.dist-info/DESCRIPTION.rst
odoo9_addon_web_translate_dialog-9.0.1.0.0.dist-info/METADATA
odoo9_addon_web_translate_dialog-9.0.1.0.0.dist-info/namespace_packages.txt
