Metadata-Version: 2.0
Name: odoo9-addon-web-translate-dialog
Version: 9.0.1.0.0
Summary: Easy-to-use pop-up to translate fields in several languages
Home-page: https://odoo-community.org/
Author: UNKNOWN
Author-email: UNKNOWN
License: AGPL-3
Platform: UNKNOWN
Requires-Dist: odoo (<9.1a,>=9.0a)
Classifier: Programming Language :: Python :: 2.7
Classifier: Framework :: Odoo
Classifier: License :: OSI Approved :: GNU Affero General Public License v3
